{
    "match" :[
         {
            "country":"italy",
            "league":"champions league",
            "homeTeam": "Fiorentina",
            "homeTeamForm":"L,W,D,L,W",
            "homeTeamPosition":"8", 
            "homeOdds": "2.6",
            "awayTeam": "Atalanta",
            "awayTeamForm":"w,D,D,L,D",
            "awayTeamPosition":"5",
             "awayOdds": "2.7",
             "totalDraws": "0",
             "TeamsInLeague": "20",
             "finalScore": "Fiorentina",
             "headtoheadOne" : {
                    "headtoheadOneHome":"Atalanta",
                    "htohOneHScore":"2",
                    "headtoheadOneAway": "Fiorentina",
                    "htohOneAScore":"3",
                    "headtoheadOneWon": "Fiorentina"
             },
             "headtoheadTwo" : {
                    "headtoheadTwoHome":"Atalanta",
                    "htohTwoHScore":"1",
                    "headtoheadTwoAway": "Fiorentina",
                    "htohTwoAScore":"2",
                    "headtoheadTwoWon": "Fiorentina" 
             },
             "headtoheadThree" : {
                    "headtoheadThreeHome":"Fiorentina",
                    "htohThreeHScore":"2",
                    "headtoheadThreeAway": "Atalanta",
                    "htohThreeAScore":"3",
                    "headtoheadThreeWon": "Atalanta"
             },
             "headtoheadFour" : {
                "headtoheadFourHome":"Atalanta",
                "htohFourHScore":"3",
                "headtoheadFourAway": "Fiorentina",
                "htohFourAScore":"0",
                "headtoheadFourWon": "Atalanta"
         }         
             
          
       }
    ]
 }